PubmedZenbu/PubmedZenbu.py
PubmedZenbu/__init__.py
PubmedZenbu/eutils.py
PubmedZenbu/use_gpt.py
PubmedZenbu-0.3.7.dist-info/LICENSE
PubmedZenbu-0.3.7.dist-info/METADATA
PubmedZenbu-0.3.7.dist-info/WHEEL
PubmedZenbu-0.3.7.dist-info/entry_points.txt
PubmedZenbu-0.3.7.dist-info/top_level.txt
PubmedZenbu-0.3.7.dist-info/RECORD
