Metadata-Version: 2.1
Name: PubmedZenbu
Version: 0.3.7
Summary: PubmedZenbu
Home-page: https://github.com/dogrun-inc/pubmed-zenbu/tree/2023_dev_suzuki
Download-URL: https://github.com/dogrun-inc/pubmed-zenbu/tree/2023_dev_suzuki
Author: Sora Yonezawa, Mitsuo Shintani, Naoya Oec, Takayuki Suzuki
Author-email: oec@dogrun.jp
Maintainer: Sora Yonezawa, Mitsuo Shintani, Naoya Oec, Takayuki Suzuki
Maintainer-email: oec@dogrun.jp
License: MIT
Keywords: pubmed scraping article dogrun
Classifier: License :: OSI Approved :: MIT License
Classifier: Programming Language :: Python :: 3.9
Classifier: Programming Language :: Python :: 3.10
Classifier: Programming Language :: Python :: 3.11
License-File: LICENSE
Requires-Dist: requests (>=2.31)
Requires-Dist: openai (<=0.28.1)
Requires-Dist: PyYAML (>=5.1)
Requires-Dist: Pandas (>=2.0.0)
